mlflow_dep_analyzer/__init__.py
mlflow_dep_analyzer/unified_analyzer.py
mlflow_dep_analyzer-0.9.0.dist-info/METADATA
mlflow_dep_analyzer-0.9.0.dist-info/WHEEL
mlflow_dep_analyzer-0.9.0.dist-info/top_level.txt
mlflow_dep_analyzer-0.9.0.dist-info/RECORD
