Metadata-Version: 2.4
Name: mlflow-dep-analyzer
Version: 0.9.0
Summary: Smart dependency analysis and minimal requirements generation for MLflow models
Author: Andrew Gross
Requires-Python: >=3.9
Requires-Dist: mlflow
